LatexTemplater/ArgParser.py
LatexTemplater/LatexGenerator.py
LatexTemplater/TemplateCore.py
LatexTemplater/TemplateFilter.py
LatexTemplater/TemplatePluginManager.py
LatexTemplater/__init__.py
LatexTemplater/__main__.py
LatexTemplater/CoreFilters/Decimal.py
LatexTemplater/CoreFilters/Equation.py
LatexTemplater/CoreFilters/Imaginary.py
LatexTemplater/CoreFilters/InlineEquation.py
LatexTemplater/CoreFilters/Matrix.py
LatexTemplater/CoreFilters/Plugin.py
LatexTemplater/CoreFilters/__init__.py
LatexTemplater-0.6.1.dist-info/LICENCE
LatexTemplater-0.6.1.dist-info/METADATA
LatexTemplater-0.6.1.dist-info/WHEEL
LatexTemplater-0.6.1.dist-info/entry_points.txt
LatexTemplater-0.6.1.dist-info/top_level.txt
LatexTemplater-0.6.1.dist-info/RECORD
