Metadata-Version: 2.1
Name: LatexTemplater
Version: 0.6.1
Summary: A package to allow python templating in latex files
Home-page: https://github.com/NathanRoseCE/LatexTemplater
Author: Nathan Rose
Author-email: mail.nathanrose@gmail.com
License: UNKNOWN
Platform: UNKNOWN
Classifier: Programming Language :: Python :: 3
Classifier: License :: OSI Approved :: MIT License
Classifier: Operating System :: POSIX :: Linux
Requires-Python: >=3.6
License-File: LICENCE
Requires-Dist: ninja2
